_version.py
openmc_data_downloader/__init__.py
openmc_data_downloader/cross_sections_directory.py
openmc_data_downloader/fendl_3.1d_cross_sections.xml
openmc_data_downloader/nndc_7.1_cross_sections.xml
openmc_data_downloader/nndc_8.0_cross_sections.xml
openmc_data_downloader/tendl_2019_cross_sections.xml
openmc_data_downloader/terminal_cmd.py
openmc_data_downloader/utils.py
openmc_data_downloader-0.6.1.dist-info/LICENSE
openmc_data_downloader-0.6.1.dist-info/METADATA
openmc_data_downloader-0.6.1.dist-info/WHEEL
openmc_data_downloader-0.6.1.dist-info/entry_points.txt
openmc_data_downloader-0.6.1.dist-info/top_level.txt
openmc_data_downloader-0.6.1.dist-info/RECORD
