Metadata-Version: 2.2
Name: openmc_data_downloader
Version: 0.6.1
Summary: A tool for selectively downloading h5 files for specified isotopes / elements from your libraries of choice
Author-email: Jonathan Shimwell <mail@jshimwell.com>
License: MIT License
Project-URL: Homepage, https://github.com/fusion-energy/openmc_data_downloader
Project-URL: Bug Tracker, https://github.com/fusion-energy/openmc_data_downloader/issues
Keywords: openmc,nuclear,data,download,process,cross,section
Classifier: Programming Language :: Python :: 3
Classifier: License :: OSI Approved :: MIT License
Classifier: Operating System :: OS Independent
Requires-Python: >=3.8
License-File: LICENSE
Requires-Dist: pandas
Requires-Dist: retry
Provides-Extra: tests
Requires-Dist: pytest; extra == "tests"
